backfillz/__init__.py
backfillz/backfillz.py
backfillz/data.py
backfillz/example/__init__.py
backfillz/example/eight_schools.py
backfillz/plot.py
backfillz/py.typed
backfillz/slice_histograms.py
backfillz/spiral_stream.py
backfillz/stan.py
backfillz/theme.py
backfillz/trace_dial.py
backfillz/trace_slice_histogram.py
backfillz-0.2.4.dist-info/LICENSE.md
backfillz-0.2.4.dist-info/WHEEL
backfillz-0.2.4.dist-info/METADATA
backfillz-0.2.4.dist-info/RECORD
