Metadata-Version: 2.1
Name: backfillz
Version: 0.2.4
Summary: MCMC visualisations package developed at the University of Warwick and supported by The Alan Turing Institute.
Home-page: https://github.com/WarwickCIM/backfillz-py
License: MIT
Author: James Tripp
Author-email: james.tripp@warwick.ac.uk
Requires-Python: >=3.9.0,<3.10
Classifier: License :: OSI Approved :: GNU General Public License v3 (GPLv3)
Classifier: License :: OSI Approved :: MIT License
Classifier: Natural Language :: English
Classifier: Programming Language :: Python :: 3
Classifier: Programming Language :: Python :: 3.9
Requires-Dist: importlib_metadata (==3.4.0)
Requires-Dist: kaleido (==0.2.1)
Requires-Dist: nbval (>=0.9.6,<0.10.0)
Requires-Dist: numpy (==1.20.3)
Requires-Dist: plotly (>=4.14.3,<5.0.0)
Requires-Dist: pystan (==3.0.0)
Requires-Dist: scipy (>=1.6.3,<2.0.0)
